README.md
setup.py
diff_priv_laplace_python.egg-info/PKG-INFO
diff_priv_laplace_python.egg-info/SOURCES.txt
diff_priv_laplace_python.egg-info/dependency_links.txt
diff_priv_laplace_python.egg-info/not-zip-safe
diff_priv_laplace_python.egg-info/requires.txt
diff_priv_laplace_python.egg-info/top_level.txt
diffpriv_laplace/__init__.py
diffpriv_laplace/exceptions.py
diffpriv_laplace/laplace_mechanism.py
diffpriv_laplace/laplace_sanitizer.py
diffpriv_laplace/statistics.py
diffpriv_laplace/version.py
diffpriv_laplace/anonymizer/__init__.py
diffpriv_laplace/anonymizer/base.py
diffpriv_laplace/anonymizer/count.py
diffpriv_laplace/anonymizer/counting.py
diffpriv_laplace/anonymizer/max.py
diffpriv_laplace/anonymizer/mean.py
diffpriv_laplace/anonymizer/median.py
diffpriv_laplace/anonymizer/min.py
diffpriv_laplace/anonymizer/proportion.py
diffpriv_laplace/anonymizer/sum.py
diffpriv_laplace/anonymizer/variance.py
diffpriv_laplace/global_sensitivity/__init__.py
diffpriv_laplace/global_sensitivity/base.py
diffpriv_laplace/global_sensitivity/count.py
diffpriv_laplace/global_sensitivity/counting.py
diffpriv_laplace/global_sensitivity/max.py
diffpriv_laplace/global_sensitivity/mean.py
diffpriv_laplace/global_sensitivity/median.py
diffpriv_laplace/global_sensitivity/min.py
diffpriv_laplace/global_sensitivity/proportion.py
diffpriv_laplace/global_sensitivity/sum.py
diffpriv_laplace/global_sensitivity/variance.py
diffpriv_laplace/query/__init__.py
diffpriv_laplace/query/parallel_statistics.py
diffpriv_laplace/query/sequential_statistics.py
tests/__init__.py
tests/unit/__init__.py
tests/unit/test_laplace_mechanism.py
tests/unit/test_laplace_sanitizer.py
tests/unit/test_statistics.py
tests/unit/anonymizer/__init__.py
tests/unit/anonymizer/test_anonymizer.py
tests/unit/anonymizer/test_count.py
tests/unit/anonymizer/test_counting.py
tests/unit/anonymizer/test_max.py
tests/unit/anonymizer/test_mean.py
tests/unit/anonymizer/test_median.py
tests/unit/anonymizer/test_min.py
tests/unit/anonymizer/test_proportion.py
tests/unit/anonymizer/test_sum.py
tests/unit/anonymizer/test_variance.py
tests/unit/global_sensitivity/__init__.py
tests/unit/global_sensitivity/test_count.py
tests/unit/global_sensitivity/test_counting.py
tests/unit/global_sensitivity/test_global_sensitivity.py
